{
  "version": 3,
  "middleware": {
    "/": {
      "files": [
        "prerender-manifest.js",
        "server/edge-runtime-webpack.js",
        "server/middleware.js"
      ],
      "name": "middleware",
      "page": "/",
      "matchers": [
        {
          "regexp": "^(?:\\/(_next\\/data\\/[^/]{1,}))?(?:\\/((?:[^\\/#\\?]+?)(?:\\/(?:[^\\/#\\?]+?))*))?(.json)?[\\/#\\?]?$",
          "originalSource": "/:path*"
        }
      ],
      "wasm": [],
      "assets": [],
      "environments": {
        "previewModeId": "9789585ef2b456bbf7f9901a7a200a85",
        "previewModeSigningKey": "553a521546acebdec76ab1bf754891aad5e26e0f0136b75dbfb2b1a22f20d1bb",
        "previewModeEncryptionKey": "c43deb63a11b7a0cfae33c281e82fe765100fdcfda6c23b505f63b06dfeec27c"
      }
    }
  },
  "functions": {},
  "sortedMiddleware": [
    "/"
  ]
}